[{"time":"2022-03-04T04:21:27.000Z","bts":"BTS_1","latitiude":"55.84949","longitude":"38.26976","rsrp":-114,"rsrq":-14.5},{"time":"2022-03-02T02:59:27.000Z","bts":"BTS_1","latitiude":"55.849247","longitude":"38.271584","rsrp":-111,"rsrq":-11.5},{"time":"2022-03-02T02:59:27.000Z","bts":"BTS_1","latitiude":"55.849","longitude":"38.270573","rsrp":-113,"rsrq":-15.5},{"time":"2022-03-06T14:44:27.000Z","bts":"BTS_2","latitiude":"55.93558","longitude":"37.333904","rsrp":-127,"rsrq":-20},{"time":"2022-03-03T12:49:26.999Z","bts":"BTS_2","latitiude":"55.93556","longitude":"37.334267","rsrp":-114,"rsrq":-18.5},{"time":"2022-03-06T14:42:27.000Z","bts":"BTS_2","latitiude":"55.935463","longitude":"37.334118","rsrp":-113,"rsrq":-16},{"time":"2022-03-06T14:42:27.000Z","bts":"BTS_2","latitiude":"55.935493","longitude":"37.33414","rsrp":-115,"rsrq":-19},{"time":"2022-03-01T10:21:27.000Z","bts":"BTS_2","latitiude":"55.93544","longitude":"37.33403","rsrp":-110,"rsrq":-11},{"time":"2022-03-06T13:02:27.000Z","bts":"BTS_2","latitiude":"55.93571","longitude":"37.33461","rsrp":-121,"rsrq":-18.5},{"time":"2022-03-01T10:46:26.999Z","bts":"BTS_2","latitiude":"55.935516","longitude":"37.33296","rsrp":-109,"rsrq":-11},{"time":"2022-03-06T13:03:27.000Z","bts":"BTS_3","latitiude":"55.935646","longitude":"37.334206","rsrp":-114,"rsrq":-20},{"time":"2022-03-03T18:34:27.000Z","bts":"BTS_4","latitiude":"55.483456","longitude":"37.45827","rsrp":-100,"rsrq":-12},{"time":"2022-03-04T11:09:26.999Z","bts":"BTS_5","latitiude":"56.184277","longitude":"37.528717","rsrp":-113,"rsrq":-12.5},{"time":"2022-03-06T08:37:27.000Z","bts":"BTS_6","latitiude":"55.810085","longitude":"38.238773","rsrp":-113,"rsrq":-14.5},{"time":"2022-03-03T12:44:27.000Z","bts":"BTS_7","latitiude":"55.69403","longitude":"37.11495","rsrp":-113,"rsrq":-10.5},{"time":"2022-03-03T12:46:26.999Z","bts":"BTS_7","latitiude":"55.69415","longitude":"37.113747","rsrp":-112,"rsrq":-10.5},{"time":"2022-03-03T12:44:27.000Z","bts":"BTS_7","latitiude":"55.694374","longitude":"37.11602","rsrp":-110,"rsrq":-10.5},{"time":"2022-02-28T08:52:27.000Z","bts":"BTS_7","latitiude":"55.697475","longitude":"37.104115","rsrp":-108,"rsrq":-17.5},{"time":"2022-03-03T09:42:26.999Z","bts":"BTS_7","latitiude":"55.699097","longitude":"37.108063","rsrp":-109,"rsrq":-9.5},{"time":"2022-03-06T08:39:27.000Z","bts":"BTS_8","latitiude":"55.972435","longitude":"37.701687","rsrp":-114,"rsrq":-16.5},{"time":"2022-03-03T08:55:27.000Z","bts":"BTS_9","latitiude":"55.881927","longitude":"38.244995","rsrp":-112,"rsrq":-14.5},{"time":"2022-03-06T13:31:26.999Z","bts":"BTS_10","latitiude":"56.003334","longitude":"37.52391","rsrp":-105,"rsrq":-13.5},{"time":"2022-03-01T12:59:27.000Z","bts":"BTS_11","latitiude":"55.9363","longitude":"37.32944","rsrp":-89,"rsrq":-14},{"time":"2022-03-06T12:05:27.000Z","bts":"BTS_12","latitiude":"55.850918","longitude":"38.269287","rsrp":-112,"rsrq":-18.5},{"time":"2022-03-06T15:17:27.000Z","bts":"BTS_13","latitiude":"55.85905","longitude":"36.52703","rsrp":-100,"rsrq":-9.5},{"time":"2022-03-06T11:49:27.000Z","bts":"BTS_14","latitiude":"55.482964","longitude":"37.463894","rsrp":-113,"rsrq":-16},{"time":"2022-03-06T12:22:27.000Z","bts":"BTS_14","latitiude":"55.482685","longitude":"37.465824","rsrp":-103,"rsrq":-11},{"time":"2022-03-06T06:22:27.000Z","bts":"BTS_14","latitiude":"55.48292","longitude":"37.46351","rsrp":-119,"rsrq":-17},{"time":"2022-03-06T12:21:27.000Z","bts":"BTS_14","latitiude":"55.481976","longitude":"37.46323","rsrp":-119,"rsrq":-18.5},{"time":"2022-03-06T06:22:27.000Z","bts":"BTS_14","latitiude":"55.481697","longitude":"37.462757","rsrp":-114,"rsrq":-15},{"time":"2022-03-06T04:56:27.000Z","bts":"BTS_14","latitiude":"55.48292","longitude":"37.463615","rsrp":-114,"rsrq":-16},{"time":"2022-02-28T03:40:27.000Z","bts":"BTS_14","latitiude":"55.48259","longitude":"37.469044","rsrp":-114,"rsrq":-14.5},{"time":"2022-03-06T08:58:27.000Z","bts":"BTS_14","latitiude":"55.48294","longitude":"37.464108","rsrp":-118,"rsrq":-17},{"time":"2022-03-06T08:29:27.000Z","bts":"BTS_14","latitiude":"55.483017","longitude":"37.46387","rsrp":-109,"rsrq":-17.5},{"time":"2022-03-05T08:33:27.000Z","bts":"BTS_14","latitiude":"55.482","longitude":"37.463184","rsrp":-113,"rsrq":-18},{"time":"2022-03-02T13:47:27.000Z","bts":"BTS_14","latitiude":"55.486237","longitude":"37.47209","rsrp":-106,"rsrq":-16},{"time":"2022-03-02T13:46:26.999Z","bts":"BTS_14","latitiude":"55.4863","longitude":"37.472134","rsrp":-111,"rsrq":-18.5},{"time":"2022-03-05T09:16:26.999Z","bts":"BTS_14","latitiude":"55.484154","longitude":"37.46885","rsrp":-105,"rsrq":-13.5},{"time":"2022-03-05T08:38:26.999Z","bts":"BTS_14","latitiude":"55.482975","longitude":"37.463852","rsrp":-111,"rsrq":-14.5},{"time":"2022-03-03T02:32:27.000Z","bts":"BTS_15","latitiude":"55.586025","longitude":"37.081947","rsrp":-64,"rsrq":-15},{"time":"2022-03-06T12:54:27.000Z","bts":"BTS_16","latitiude":"55.71988","longitude":"36.98657","rsrp":-117,"rsrq":-13},{"time":"2022-03-05T09:49:26.999Z","bts":"BTS_17","latitiude":"55.970387","longitude":"37.698128","rsrp":-109,"rsrq":-14},{"time":"2022-03-03T08:00:27.000Z","bts":"BTS_18","latitiude":"55.97825","longitude":"37.522797","rsrp":-101,"rsrq":-19},{"time":"2022-03-06T02:33:27.000Z","bts":"BTS_19","latitiude":"55.45908","longitude":"37.521828","rsrp":-80,"rsrq":-16.5},{"time":"2022-03-02T16:16:27.000Z","bts":"BTS_20","latitiude":"55.550095","longitude":"37.257427","rsrp":-111,"rsrq":-15},{"time":"2022-03-01T07:57:27.000Z","bts":"BTS_21","latitiude":"55.4832","longitude":"37.476166","rsrp":-89,"rsrq":-14},{"time":"2022-03-03T03:32:26.999Z","bts":"BTS_22","latitiude":"55.526814","longitude":"37.67431","rsrp":-101,"rsrq":-11.5},{"time":"2022-02-28T06:24:27.000Z","bts":"BTS_23","latitiude":"55.482","longitude":"37.46297","rsrp":-116,"rsrq":-17.5},{"time":"2022-03-06T08:29:27.000Z","bts":"BTS_23","latitiude":"55.48213","longitude":"37.463207","rsrp":-117,"rsrq":-20},{"time":"2022-02-28T05:09:26.999Z","bts":"BTS_24","latitiude":"55.70368","longitude":"37.077614","rsrp":-89,"rsrq":-14},{"time":"2022-02-28T05:09:26.999Z","bts":"BTS_24","latitiude":"55.70368","longitude":"37.077614","rsrp":-89,"rsrq":-16.5},{"time":"2022-03-06T18:30:27.000Z","bts":"BTS_25","latitiude":"55.451572","longitude":"37.604313","rsrp":-109,"rsrq":-16.5},{"time":"2022-03-02T07:17:26.999Z","bts":"BTS_26","latitiude":"55.526814","longitude":"37.67431","rsrp":-93,"rsrq":-12.5},{"time":"2022-03-03T09:48:27.000Z","bts":"BTS_26","latitiude":"55.526814","longitude":"37.67431","rsrp":-108,"rsrq":-17},{"time":"2022-03-01T13:55:27.000Z","bts":"BTS_26","latitiude":"55.526814","longitude":"37.67431","rsrp":-90,"rsrq":-14.5},{"time":"2022-03-05T19:20:26.999Z","bts":"BTS_27","latitiude":"55.648487","longitude":"37.881397","rsrp":-107,"rsrq":-16},{"time":"2022-03-05T09:43:27.000Z","bts":"BTS_28","latitiude":"55.699795","longitude":"37.1036","rsrp":-114,"rsrq":-14.5},{"time":"2022-03-02T05:02:26.999Z","bts":"BTS_29","latitiude":"55.961018","longitude":"36.94406","rsrp":-94,"rsrq":-12},{"time":"2022-02-28T18:54:27.000Z","bts":"BTS_30","latitiude":"55.456818","longitude":"37.526165","rsrp":-108,"rsrq":-15.5},{"time":"2022-03-02T12:54:27.000Z","bts":"BTS_31","latitiude":"55.75806","longitude":"38.137127","rsrp":-117,"rsrq":-16.5},{"time":"2022-03-05T20:06:27.000Z","bts":"BTS_32","latitiude":"55.8889","longitude":"37.986687","rsrp":-109,"rsrq":-13.5},{"time":"2022-03-05T20:07:27.000Z","bts":"BTS_32","latitiude":"55.888954","longitude":"37.986496","rsrp":-113,"rsrq":-15},{"time":"2022-03-03T02:18:27.000Z","bts":"BTS_32","latitiude":"55.88539","longitude":"37.988018","rsrp":-114,"rsrq":-15},{"time":"2022-02-28T09:54:27.000Z","bts":"BTS_33","latitiude":"55.848816","longitude":"38.27188","rsrp":-113,"rsrq":-19.5},{"time":"2022-03-03T12:02:27.000Z","bts":"BTS_34","latitiude":"55.48333","longitude":"37.478634","rsrp":-98,"rsrq":-18},{"time":"2022-03-05T11:22:27.000Z","bts":"BTS_34","latitiude":"55.482845","longitude":"37.454647","rsrp":-88,"rsrq":-18.5},{"time":"2022-03-03T08:37:27.000Z","bts":"BTS_34","latitiude":"55.479454","longitude":"37.470932","rsrp":-94,"rsrq":-18.5},{"time":"2022-02-28T05:31:26.999Z","bts":"BTS_34","latitiude":"55.48307","longitude":"37.47385","rsrp":-97,"rsrq":-18},{"time":"2022-03-02T12:51:27.000Z","bts":"BTS_34","latitiude":"55.483337","longitude":"37.478527","rsrp":-91,"rsrq":-14},{"time":"2022-03-02T13:52:27.000Z","bts":"BTS_35","latitiude":"55.48641","longitude":"37.471962","rsrp":-116,"rsrq":-15.5},{"time":"2022-03-06T12:12:27.000Z","bts":"BTS_36","latitiude":"56.081966","longitude":"36.712147","rsrp":-114,"rsrq":-11.5},{"time":"2022-03-03T01:57:27.000Z","bts":"BTS_37","latitiude":"55.551994","longitude":"37.258373","rsrp":-105,"rsrq":-15.5},{"time":"2022-03-03T02:13:27.000Z","bts":"BTS_37","latitiude":"55.55213","longitude":"37.258244","rsrp":-107,"rsrq":-12.5},{"time":"2022-03-03T02:12:26.999Z","bts":"BTS_37","latitiude":"55.55213","longitude":"37.258244","rsrp":-107,"rsrq":-16.5},{"time":"2022-03-05T10:24:26.999Z","bts":"BTS_37","latitiude":"55.552227","longitude":"37.25831","rsrp":-116,"rsrq":-16.5},{"time":"2022-03-03T02:02:26.999Z","bts":"BTS_37","latitiude":"55.55213","longitude":"37.258244","rsrp":-106,"rsrq":-15},{"time":"2022-03-06T07:00:27.000Z","bts":"BTS_37","latitiude":"55.55315","longitude":"37.25453","rsrp":-97,"rsrq":-11},{"time":"2022-03-05T13:35:27.000Z","bts":"BTS_37","latitiude":"55.55371","longitude":"37.256184","rsrp":-87,"rsrq":-14.5},{"time":"2022-03-05T13:35:27.000Z","bts":"BTS_37","latitiude":"55.553528","longitude":"37.255753","rsrp":-87,"rsrq":-16},{"time":"2022-03-06T08:04:27.000Z","bts":"BTS_37","latitiude":"55.552486","longitude":"37.258244","rsrp":-106,"rsrq":-18.5},{"time":"2022-03-06T07:00:27.000Z","bts":"BTS_37","latitiude":"55.55314","longitude":"37.25453","rsrp":-90,"rsrq":-14},{"time":"2022-03-05T13:34:26.999Z","bts":"BTS_37","latitiude":"55.553257","longitude":"37.25494","rsrp":-86,"rsrq":-13},{"time":"2022-03-06T10:14:27.000Z","bts":"BTS_37","latitiude":"55.552273","longitude":"37.258373","rsrp":-110,"rsrq":-18},{"time":"2022-03-06T08:05:26.999Z","bts":"BTS_37","latitiude":"55.552227","longitude":"37.258266","rsrp":-107,"rsrq":-13.5},{"time":"2022-03-05T06:50:27.000Z","bts":"BTS_37","latitiude":"55.553185","longitude":"37.25477","rsrp":-95,"rsrq":-7},{"time":"2022-03-02T16:46:26.999Z","bts":"BTS_37","latitiude":"55.55286","longitude":"37.257362","rsrp":-102,"rsrq":-18},{"time":"2022-03-05T06:58:27.000Z","bts":"BTS_37","latitiude":"55.55196","longitude":"37.25822","rsrp":-106,"rsrq":-16},{"time":"2022-03-05T13:34:26.999Z","bts":"BTS_37","latitiude":"55.553043","longitude":"37.254982","rsrp":-86,"rsrq":-12},{"time":"2022-03-06T08:05:26.999Z","bts":"BTS_37","latitiude":"55.55224","longitude":"37.258266","rsrp":-107,"rsrq":-15},{"time":"2022-03-06T06:59:27.000Z","bts":"BTS_37","latitiude":"55.553078","longitude":"37.25464","rsrp":-94,"rsrq":-15.5},{"time":"2022-03-05T10:30:27.000Z","bts":"BTS_37","latitiude":"55.550575","longitude":"37.254723","rsrp":-104,"rsrq":-18},{"time":"2022-03-05T10:39:27.000Z","bts":"BTS_37","latitiude":"55.550735","longitude":"37.254875","rsrp":-97,"rsrq":-13.5},{"time":"2022-03-06T08:10:27.000Z","bts":"BTS_37","latitiude":"55.553688","longitude":"37.255817","rsrp":-91,"rsrq":-12},{"time":"2022-03-06T08:07:27.000Z","bts":"BTS_37","latitiude":"55.55222","longitude":"37.258266","rsrp":-106,"rsrq":-14},{"time":"2022-03-06T08:10:27.000Z","bts":"BTS_37","latitiude":"55.553257","longitude":"37.254787","rsrp":-97,"rsrq":-9.5},{"time":"2022-03-02T09:34:27.000Z","bts":"BTS_38","latitiude":"55.55065","longitude":"38.009132","rsrp":-119,"rsrq":-18},{"time":"2022-03-03T04:31:26.999Z","bts":"BTS_38","latitiude":"55.55212","longitude":"38.00585","rsrp":-107,"rsrq":-14},{"time":"2022-03-03T04:35:27.000Z","bts":"BTS_38","latitiude":"55.551315","longitude":"38.010956","rsrp":-112,"rsrq":-15.5},{"time":"2022-03-05T16:53:26.999Z","bts":"BTS_38","latitiude":"55.551155","longitude":"38.010357","rsrp":-120,"rsrq":-18.5},{"time":"2022-03-03T15:02:27.000Z","bts":"BTS_39","latitiude":"56.001167","longitude":"37.522346","rsrp":-108,"rsrq":-12},{"time":"2022-03-03T10:15:27.000Z","bts":"BTS_39","latitiude":"56.001854","longitude":"37.52153","rsrp":-109,"rsrq":-13.5},{"time":"2022-03-02T14:55:27.000Z","bts":"BTS_39","latitiude":"56.003506","longitude":"37.5223","rsrp":-115,"rsrq":-16},{"time":"2022-03-06T13:31:26.999Z","bts":"BTS_39","latitiude":"56.00347","longitude":"37.522366","rsrp":-111,"rsrq":-15.5},{"time":"2022-03-01T14:46:27.000Z","bts":"BTS_39","latitiude":"56.00344","longitude":"37.522495","rsrp":-107,"rsrq":-11},{"time":"2022-03-03T14:45:27.000Z","bts":"BTS_39","latitiude":"56.002026","longitude":"37.521423","rsrp":-115,"rsrq":-12.5},{"time":"2022-03-03T11:00:27.000Z","bts":"BTS_39","latitiude":"56.002434","longitude":"37.520737","rsrp":-105,"rsrq":-9.5},{"time":"2022-03-04T06:44:27.000Z","bts":"BTS_39","latitiude":"56.002754","longitude":"37.52024","rsrp":-112,"rsrq":-10},{"time":"2022-03-01T14:44:27.000Z","bts":"BTS_39","latitiude":"56.001907","longitude":"37.52629","rsrp":-105,"rsrq":-11.5},{"time":"2022-03-02T14:57:26.999Z","bts":"BTS_39","latitiude":"56.001232","longitude":"37.52479","rsrp":-115,"rsrq":-13},{"time":"2022-03-05T16:15:27.000Z","bts":"BTS_39","latitiude":"55.9862","longitude":"37.51902","rsrp":-117,"rsrq":-15}]